pygrist_mini/__init__.py
pygrist_mini/py.typed
pygrist_mini-2026.1.1.dist-info/METADATA
pygrist_mini-2026.1.1.dist-info/WHEEL
pygrist_mini-2026.1.1.dist-info/licenses/LICENSE
pygrist_mini-2026.1.1.dist-info/RECORD
