Metadata-Version: 2.4
Name: pygrist_mini
Version: 2026.1.1
Summary: Minimal Grist API (document) client
Author-email: Andreas Kloeckner <inform@tiker.net>
License-Expression: MIT
License-File: LICENSE
Classifier: Development Status :: 3 - Alpha
Classifier: Natural Language :: English
Classifier: Operating System :: OS Independent
Classifier: Programming Language :: Python
Classifier: Programming Language :: Python :: 3
Requires-Python: >=3.10
Requires-Dist: requests~=2.31
Provides-Extra: dev
Requires-Dist: ruff>=0.9.2; extra == 'dev'
